pyregister/__init__.py
pyregister/construct_utils.py
pyregister/lazy.py
pyregister/params.py
pyregister/registrable.py
pyregister-0.0.5.dist-info/METADATA
pyregister-0.0.5.dist-info/WHEEL
pyregister-0.0.5.dist-info/top_level.txt
pyregister-0.0.5.dist-info/RECORD
