Metadata-Version: 2.1
Name: pyregister
Version: 0.0.5
Summary: A tool for automatically registering Python classes.
Author: Jiamu Zhou
Author-email: zhoujm99@gmail.com
Keywords: auto-register,register
Requires-Python: >=3.5
